neodroidvision/__init__.py
neodroidvision/classification/__init__.py
neodroidvision/classification/architectures/__init__.py
neodroidvision/classification/architectures/other_retrain.py
neodroidvision/classification/architectures/resnet_retrain.py
neodroidvision/classification/architectures/squeezenet_retrain.py
neodroidvision/classification/architectures/torus/__init__.py
neodroidvision/classification/architectures/torus/conv.py
neodroidvision/classification/loss_functions/__init__.py
neodroidvision/classification/loss_functions/center_loss.py
neodroidvision/classification/loss_functions/confidence_loss.py
neodroidvision/classification/loss_functions/ranking/__init__.py
neodroidvision/classification/loss_functions/ranking/pairwise_ranking_loss.py
neodroidvision/classification/mechanims/__init__.py
neodroidvision/classification/mechanims/attention/__init__.py
neodroidvision/classification/mechanims/attention/foveal/__init__.py
neodroidvision/classification/mechanims/attention/foveal/architecture/__init__.py
neodroidvision/classification/mechanims/attention/foveal/architecture/ram.py
neodroidvision/classification/mechanims/attention/foveal/architecture/ram_modules.py
neodroidvision/classification/mechanims/attention/self/__init__.py
neodroidvision/classification/mechanims/attention/self/self_attention.py
neodroidvision/classification/mechanims/attention/self/spectral_norm.py
neodroidvision/classification/procedures/__init__.py
neodroidvision/classification/procedures/classification_procedures.py
neodroidvision/classification/procedures/deprec/__init__.py
neodroidvision/classification/procedures/deprec/procedures.py
neodroidvision/data/__init__.py
neodroidvision/data/classification/__init__.py
neodroidvision/data/classification/dict_image_folder.py
neodroidvision/data/classification/mnist.py
neodroidvision/data/classification/vgg_face2.py
neodroidvision/data/classification/deprec/__init__.py
neodroidvision/data/classification/deprec/s_mnist.py
NeodroidVision-0.3.0.dist-info/LICENSE.md
NeodroidVision-0.3.0.dist-info/METADATA
NeodroidVision-0.3.0.dist-info/WHEEL
NeodroidVision-0.3.0.dist-info/entry_points.txt
NeodroidVision-0.3.0.dist-info/top_level.txt
NeodroidVision-0.3.0.dist-info/RECORD
