Metadata-Version: 2.1
Name: NeodroidVision
Version: 0.3.0
Summary: Computer Vision algorithm implementations, intended for use with the Neodroid platform
Home-page: https://github.com/aivclab/vision
Download-URL: https://github.com/aivclab/vision/releases
Author: Christian Heider Nielsen
Author-email: christian.heider@alexandra.dk
Maintainer: Christian Heider Nielsen
Maintainer-email: christian.heider@alexandra.dk
License: Apache License, Version 2.0
Keywords: python computer vision neo droid
Classifier: Development Status :: 4 - Beta
Classifier: Environment :: Console
Classifier: Intended Audience :: End Users/Desktop
Classifier: Intended Audience :: Developers
Classifier: License :: OSI Approved :: Apache Software License
Classifier: Operating System :: MacOS :: MacOS X
Classifier: Operating System :: Microsoft :: Windows
Classifier: Operating System :: POSIX
Classifier: Operating System :: OS Independent
Classifier: Programming Language :: Python :: 3
Classifier: Natural Language :: English
Requires-Python: >=3.6
License-File: LICENSE.md
Requires-Dist: devpack
Requires-Dist: neodroid
Requires-Dist: numpy (>=1.20.2)
Requires-Dist: scipy
Requires-Dist: scikit-image
Requires-Dist: tqdm
Requires-Dist: Pillow (>=9.0.0)
Requires-Dist: matplotlib (>=3.4.1)
Requires-Dist: pip
Requires-Dist: h5py
Requires-Dist: torch (>=1.11.0)
Requires-Dist: torchvision
Requires-Dist: pycocotools (>=2.0.2)
Requires-Dist: albumentations (>=0.5.2)
Requires-Dist: opencv-python (>=4.5.1.48)
Requires-Dist: seaborn
Requires-Dist: munin
Requires-Dist: PyWavelets
Requires-Dist: imageio
Requires-Dist: pypng
Requires-Dist: sorcery
Requires-Dist: black[jupyter]
Provides-Extra: all
Requires-Dist: mock ; extra == 'all'
Requires-Dist: dlib ; extra == 'all'
Requires-Dist: scipy ; extra == 'all'
Requires-Dist: sphinxcontrib-programoutput ; extra == 'all'
Requires-Dist: pycocotools (>=2.0.2) ; extra == 'all'
Requires-Dist: pip (>=19.0.3) ; extra == 'all'
Requires-Dist: torchvision ; extra == 'all'
Requires-Dist: albumentations (>=0.5.2) ; extra == 'all'
Requires-Dist: numpy (>=1.20.2) ; extra == 'all'
Requires-Dist: black[jupyter] (>=21.5b0) ; extra == 'all'
Requires-Dist: tqdm ; extra == 'all'
Requires-Dist: munin ; extra == 'all'
Requires-Dist: neodroid ; extra == 'all'
Requires-Dist: matplotlib (>=3.4.1) ; extra == 'all'
Requires-Dist: wheel (>=0.33.0) ; extra == 'all'
Requires-Dist: kivy ; extra == 'all'
Requires-Dist: h5py ; extra == 'all'
Requires-Dist: PyWavelets ; extra == 'all'
Requires-Dist: pytest (>=4.4.1) ; extra == 'all'
Requires-Dist: sorcery ; extra == 'all'
Requires-Dist: sphinx (>=4.0.1) ; extra == 'all'
Requires-Dist: opencv-python (>=4.5.1.48) ; extra == 'all'
Requires-Dist: twine (>=1.13.0) ; extra == 'all'
Requires-Dist: imageio ; extra == 'all'
Requires-Dist: black[jupyter] ; extra == 'all'
Requires-Dist: Pillow (>=9.0.0) ; extra == 'all'
Requires-Dist: pycocotools ; extra == 'all'
Requires-Dist: pypng ; extra == 'all'
Requires-Dist: scikit-image ; extra == 'all'
Requires-Dist: torch (>=1.11.0) ; extra == 'all'
Requires-Dist: pytest (>=4.3.0) ; extra == 'all'
Requires-Dist: pre-commit ; extra == 'all'
Requires-Dist: seaborn ; extra == 'all'
Requires-Dist: polyscope (>=0.1.6) ; extra == 'all'
Requires-Dist: coveralls (>=1.6.0) ; extra == 'all'
Requires-Dist: pytest-cov (>=2.11.1) ; extra == 'all'
Requires-Dist: pip ; extra == 'all'
Requires-Dist: pygame ; extra == 'all'
Provides-Extra: dev
Requires-Dist: mock ; extra == 'dev'
Requires-Dist: scipy ; extra == 'dev'
Requires-Dist: sphinxcontrib-programoutput ; extra == 'dev'
Requires-Dist: pycocotools (>=2.0.2) ; extra == 'dev'
Requires-Dist: pip (>=19.0.3) ; extra == 'dev'
Requires-Dist: torchvision ; extra == 'dev'
Requires-Dist: albumentations (>=0.5.2) ; extra == 'dev'
Requires-Dist: numpy (>=1.20.2) ; extra == 'dev'
Requires-Dist: black[jupyter] (>=21.5b0) ; extra == 'dev'
Requires-Dist: tqdm ; extra == 'dev'
Requires-Dist: munin ; extra == 'dev'
Requires-Dist: neodroid ; extra == 'dev'
Requires-Dist: matplotlib (>=3.4.1) ; extra == 'dev'
Requires-Dist: wheel (>=0.33.0) ; extra == 'dev'
Requires-Dist: kivy ; extra == 'dev'
Requires-Dist: h5py ; extra == 'dev'
Requires-Dist: PyWavelets ; extra == 'dev'
Requires-Dist: pytest (>=4.4.1) ; extra == 'dev'
Requires-Dist: sorcery ; extra == 'dev'
Requires-Dist: sphinx (>=4.0.1) ; extra == 'dev'
Requires-Dist: opencv-python (>=4.5.1.48) ; extra == 'dev'
Requires-Dist: twine (>=1.13.0) ; extra == 'dev'
Requires-Dist: imageio ; extra == 'dev'
Requires-Dist: black[jupyter] ; extra == 'dev'
Requires-Dist: Pillow (>=9.0.0) ; extra == 'dev'
Requires-Dist: pycocotools ; extra == 'dev'
Requires-Dist: pypng ; extra == 'dev'
Requires-Dist: scikit-image ; extra == 'dev'
Requires-Dist: torch (>=1.11.0) ; extra == 'dev'
Requires-Dist: pytest (>=4.3.0) ; extra == 'dev'
Requires-Dist: pre-commit ; extra == 'dev'
Requires-Dist: seaborn ; extra == 'dev'
Requires-Dist: polyscope (>=0.1.6) ; extra == 'dev'
Requires-Dist: coveralls (>=1.6.0) ; extra == 'dev'
Requires-Dist: pytest-cov (>=2.11.1) ; extra == 'dev'
Requires-Dist: pip ; extra == 'dev'
Requires-Dist: pygame ; extra == 'dev'
Provides-Extra: docs
Requires-Dist: sphinx (>=4.0.1) ; extra == 'docs'
Requires-Dist: sphinxcontrib-programoutput ; extra == 'docs'
Provides-Extra: extra
Requires-Dist: polyscope (>=0.1.6) ; extra == 'extra'
Requires-Dist: pycocotools ; extra == 'extra'
Provides-Extra: gui
Requires-Dist: pygame ; extra == 'gui'
Requires-Dist: kivy ; extra == 'gui'
Requires-Dist: imageio ; extra == 'gui'
Provides-Extra: samples
Requires-Dist: dlib ; extra == 'samples'
Provides-Extra: setup
Provides-Extra: tests
Requires-Dist: mock ; extra == 'tests'
Requires-Dist: pytest (>=4.4.1) ; extra == 'tests'
